poi/__init__.py
poi/_poi.py
poi_clustering-0.0.6.dist-info/METADATA
poi_clustering-0.0.6.dist-info/WHEEL
poi_clustering-0.0.6.dist-info/top_level.txt
poi_clustering-0.0.6.dist-info/RECORD
