Metadata-Version: 2.1
Name: poi-clustering
Version: 0.0.6
Summary: Point-of-Interest clustering from GPS trajectories
Home-page: https://github.com/woohyeok-choi/poi-clustering
Author: Woohyeok Choi
Author-email: woohyeok.choi@kaist.ac.kr
License: UNKNOWN
Platform: UNKNOWN
Classifier: Programming Language :: Python :: 3
Classifier: Topic :: Scientific/Engineering
Requires-Python: >=3.6
Requires-Dist: numpy
Requires-Dist: scikit-learn
